exchange.py
exchange-0.3.dist-info/DESCRIPTION.rst
exchange-0.3.dist-info/METADATA
exchange-0.3.dist-info/metadata.json
exchange-0.3.dist-info/RECORD
exchange-0.3.dist-info/top_level.txt
exchange-0.3.dist-info/WHEEL
